[{"_path":"/articles","_dir":"","_draft":false,"_partial":false,"_locale":"","title":"Articles","description":"","layout":"page","path":"~/articles","_type":"markdown","_id":"content:articles:index.md","_source":"content","_file":"articles/index.md","_extension":"md"},{"_path":"/communications","_dir":"","_draft":false,"_partial":false,"_locale":"","title":"Communications","description":"A list of our most recent emails.","layout":"page","_type":"markdown","_id":"content:communications:index.md","_source":"content","_file":"communications/index.md","_extension":"md"}]