[{"_path":"/contactsgoogleform","_dir":"","_draft":false,"_partial":false,"_locale":"","title":"Contacts","description":"","layout":"default","head":{"title":"The Rodys - Contact Page"},"_type":"markdown","_id":"content:3.ContactsGoogleForm.md","_source":"content","_file":"3.ContactsGoogleForm.md","_extension":"md"},{"_path":"/articles/discipline","_dir":"articles","_draft":false,"_partial":false,"_locale":"","title":"Discipline","description":"The alternative to punishment.","cover":null,"author":{"name":"MSRody","avatarUrl":"public/MikeWithMicBlue_sm.jpg","link":"https://www.facebook.com/mike.rody"},"date":"2024-01-09T00:00:00.000Z","layout":"article","_type":"markdown","_id":"content:articles:1.discipline.md","_source":"content","_file":"articles/1.discipline.md","_extension":"md"}]